Metadata-Version: 1.0
Name: openvision
Version: 0.0.0
Summary: Open vision.
Home-page: UNKNOWN
Author: ZQPei
Author-email: peiziqiang@gmail.com
License: MIT
Platform: all
